md_caba/__init__.py
md_caba/core.py
md_caba-0.1.2.dist-info/METADATA
md_caba-0.1.2.dist-info/WHEEL
md_caba-0.1.2.dist-info/top_level.txt
md_caba-0.1.2.dist-info/RECORD
