Metadata-Version: 2.1
Name: md_caba
Version: 0.1.2
Summary: 一个简单的Markdown文件读取和解析工具
Home-page: https://github.com/CaBa52052/md_caba
Author: CaBa52052
Author-email: CaBa52052@qq.com
Classifier: Programming Language :: Python :: 3
Classifier: License :: OSI Approved :: MIT License
Classifier: Operating System :: OS Independent
Requires-Dist: markdown>=3.3.0
